{
 "absolute_value": 0,
 "align_labels_right": 0,
 "creation": "2025-07-12 18:22:41.427069",
 "css": "body {\n    font-family: Arial, sans-serif;\n    margin: 0;\n    padding: 0;\n    background-color: #f4f4f9;\n}\n\n.salary-slip {\n    width: 80%;\n    margin: 50px auto;\n    background-color: #fff;\n    border: 1px solid #ddd;\n    padding: 20px;\n    box-shadow: 0px 0px 15px rgba(0, 0, 0, 0.1);\n}\n\nh2, h3 {\n    text-align: center;\n    margin: 0;\n}\n\n.employee-details {\n    margin-bottom: 20px;\n}\n\n.employee-details p {\n    margin: 5px 0;\n}\n\ntable {\n    width: 100%;\n    border-collapse: collapse;\n    margin: 20px 0;\n}\n\ntable, th, td {\n    border: 1px solid #ddd;\n}\n\nth, td {\n    padding: 10px;\n    text-align: left;\n}\n\nth {\n    background-color: #f2f2f2;\n}\n\n.total {\n    text-align: right;\n    margin-top: 20px;\n}\n\n.total p {\n    font-size: 18px;\n    font-weight: bold;\n}\n",
 "custom_format": 1,
 "default_print_language": "en",
 "disabled": 0,
 "doc_type": "Pay Slips",
 "docstatus": 0,
 "doctype": "Print Format",
 "font_size": 14,
 "html": "<!DOCTYPE html>\n<html lang=\"en\">\n<head>\n    <meta charset=\"UTF-8\">\n    <meta name=\"viewport\" content=\"width=device-width, initial-scale=1.0\">\n    <title>Salary Slip</title>\n    \n</head>\n<body>\n    <div class=\"salary-slip\">\n        <h2>Opticodes Technologies Private Limited</h2>\n        <p>65/65 Mod Mohal, Kanpur 208001</p>\n        <h3>Salary Slip for {{ month }} {{ year }}</h3>\n\n        <div class=\"employee-details\">\n            <p><strong>Name:</strong> {{ employee_name }}</p>\n            <p><strong>Email ID:</strong> {{ email }}</p>\n            <p><strong>Designation:</strong> {{ designation }}</p>\n            <p><strong>Department:</strong> {{ department }}</p>\n            <p><strong>Date of Joining:</strong> {{ joining_date }}</p>\n            <p><strong>Basic Salary | Per Day Rate:</strong> {{ basic_salary }} | {{ per_day_rate }}</p>\n        </div>\n\n        <table>\n            <thead>\n                <tr>\n                    <th>Particulars</th>\n                    <th>Days</th>\n                    <th>Rate</th>\n                    <th>Effective Percent</th>\n                    <th>Amount</th>\n                </tr>\n            </thead>\n            <tbody>\n                <tr>\n                    <td>Full Day Working</td>\n                    <td>{{ full_day_working.days }}</td>\n                    <td>{{ full_day_working.rate }}</td>\n                    <td>{{ full_day_working.effective_percent }}</td>\n                    <td>{{ full_day_working.amount }}</td>\n                </tr>\n                <tr>\n                    <td>Half Day Working</td>\n                    <td>{{ half_day_working.days }}</td>\n                    <td>{{ half_day_working.rate }}</td>\n                    <td>{{ half_day_working.effective_percent }}</td>\n                    <td>{{ half_day_working.amount }}</td>\n                </tr>\n                <!-- Add other rows like 3/4 Day Working, Quarter Day Working, etc. -->\n            </tbody>\n        </table>\n\n        <div class=\"other-earnings\">\n            <h4>C) Other Earnings</h4>\n            <table>\n                <thead>\n                    <tr>\n                        <th>Particulars</th>\n                        <th>Amount</th>\n                    </tr>\n                </thead>\n                <tbody>\n                    <tr>\n                        <td>Incentive</td>\n                        <td>{{ other_earnings.incentive }}</td>\n                    </tr>\n                    <tr>\n                        <td>Project Deadline Allowance</td>\n                        <td>{{ other_earnings.project_deadline_allowance }}</td>\n                    </tr>\n                </tbody>\n            </table>\n        </div>\n\n        <div class=\"total\">\n            <p><strong>Net Amount Payable:</strong> {{ net_amount }}</p>\n        </div>\n    </div>\n</body>\n</html>",
 "idx": 0,
 "line_breaks": 0,
 "margin_bottom": 15.0,
 "margin_left": 15.0,
 "margin_right": 15.0,
 "margin_top": 15.0,
 "modified": "2025-07-12 18:25:12.166679",
 "modified_by": "Administrator",
 "module": "Pinnaclehrms",
 "name": "Pay Slip Format",
 "owner": "Administrator",
 "page_number": "Hide",
 "pdf_generator": "wkhtmltopdf",
 "print_format_builder": 0,
 "print_format_builder_beta": 0,
 "print_format_type": "Jinja",
 "raw_printing": 0,
 "show_section_headings": 0,
 "standard": "Yes"
}